blox-0.2.1.dist-info/METADATA
blox-0.2.1.dist-info/top_level.txt
blox-0.2.1.dist-info/DESCRIPTION.rst
blox-0.2.1.dist-info/metadata.json
blox-0.2.1.dist-info/WHEEL
blox-0.2.1.dist-info/RECORD
blox/dom.py
blox/text.py
blox/document.py
blox/all.py
blox/attributes.py
blox/shpaml.py
blox/__init__.py
blox/builder.py
blox/compile.py
blox/base.py
